git_ranch/__init__.py
git_ranch/__main__.py
git_ranch-1.0.2.dist-info/LICENSE
git_ranch-1.0.2.dist-info/METADATA
git_ranch-1.0.2.dist-info/WHEEL
git_ranch-1.0.2.dist-info/entry_points.txt
git_ranch-1.0.2.dist-info/top_level.txt
git_ranch-1.0.2.dist-info/RECORD
